bearish/__init__.py
bearish/database/__init__.py
bearish/database/alembic/README
bearish/database/alembic/alembic.ini
bearish/database/alembic/env.py
bearish/database/alembic/script.py.mako
bearish/database/alembic/versions/0a4bbaa82cd1_sec.py
bearish/database/alembic/versions/4e44f10ee322_price_etf.py
bearish/database/alembic/versions/5f6984590216_price_growth.py
bearish/database/alembic/versions/79d40a2eeef5_index_table.py
bearish/database/alembic/versions/b62d0afd2675_price_growth.py
bearish/database/alembic/versions/ca2d5f47456a_price_index.py
bearish/database/alembic/versions/f7b416c59e27_sec_value.py
bearish/database/alembic/versions/f94459e49cae_price_etf.py
bearish/database/crud.py
bearish/database/schemas.py
bearish/database/scripts/create_revision.py
bearish/database/scripts/upgrade.py
bearish/database/settings.py
bearish/exceptions.py
bearish/exchanges/__init__.py
bearish/exchanges/exchanges.py
bearish/interface/__init__.py
bearish/interface/interface.py
bearish/main.py
bearish/models/__init__.py
bearish/models/api_keys/__init__.py
bearish/models/api_keys/api_keys.py
bearish/models/assets/__init__.py
bearish/models/assets/assets.py
bearish/models/assets/base.py
bearish/models/assets/crypto.py
bearish/models/assets/currency.py
bearish/models/assets/equity.py
bearish/models/assets/etfs.py
bearish/models/assets/index.py
bearish/models/base.py
bearish/models/financials/__init__.py
bearish/models/financials/balance_sheet.py
bearish/models/financials/base.py
bearish/models/financials/cash_flow.py
bearish/models/financials/earnings_date.py
bearish/models/financials/metrics.py
bearish/models/price/__init__.py
bearish/models/price/price.py
bearish/models/price/prices.py
bearish/models/query/__init__.py
bearish/models/query/query.py
bearish/models/sec/SUBMISSION.tsv
bearish/models/sec/__init__.py
bearish/models/sec/ciks.py
bearish/models/sec/sec.py
bearish/sources/__init__.py
bearish/sources/base.py
bearish/sources/financedatabase.py
bearishpy-0.45.0.dist-info/METADATA
bearishpy-0.45.0.dist-info/WHEEL
bearishpy-0.45.0.dist-info/entry_points.txt
bearishpy-0.45.0.dist-info/licenses/LICENSE
bearishpy-0.45.0.dist-info/RECORD
