Metadata-Version: 2.4
Name: bearishpy
Version: 0.45.0
Summary: 
License-File: LICENSE
Author: aan
Author-email: andoludovic.andriamamonjy@gmail.com
Requires-Python: >=3.11,<3.13
Classifier: Programming Language :: Python :: 3
Classifier: Programming Language :: Python :: 3.11
Classifier: Programming Language :: Python :: 3.12
Requires-Dist: alembic (>=1.14.0,<2.0.0)
Requires-Dist: html5lib (>=1.1,<2.0)
Requires-Dist: numpy (==2.2.6)
Requires-Dist: pandas (>=2.1.4,<3.0.0)
Requires-Dist: pydantic (>=2.5.3,<3.0.0)
Requires-Dist: python-dotenv (>=1.0.1,<2.0.0)
Requires-Dist: sec-cik-mapper (>=2.1.0,<3.0.0)
Requires-Dist: sec-edgar-downloader (>=5.0.3,<6.0.0)
Requires-Dist: setuptools (>=78.1.0,<79.0.0)
Requires-Dist: sqlmodel (>=0.0.22,<0.0.23)
Requires-Dist: tenacity (>=9.0.0,<10.0.0)
Requires-Dist: typeguard (>=4.1.5,<5.0.0)
Requires-Dist: typer (>=0.13.1,<0.14.0)
Requires-Dist: unidecode (>=1.3.8,<2.0.0)
Requires-Dist: yahooquery (>=2.4.1,<3.0.0)
Requires-Dist: yfinance (>=0.2.66,<0.3.0)
